seqme/__init__.py
seqme/py.typed
seqme/core/__init__.py
seqme/core/base.py
seqme/core/io.py
seqme/core/pareto.py
seqme/core/plots.py
seqme/core/tables.py
seqme/metrics/__init__.py
seqme/metrics/authenticity.py
seqme/metrics/conformity_score.py
seqme/metrics/count.py
seqme/metrics/diversity.py
seqme/metrics/fbd.py
seqme/metrics/fkea.py
seqme/metrics/fold.py
seqme/metrics/hitrate.py
seqme/metrics/hypervolume.py
seqme/metrics/id.py
seqme/metrics/jaccard_similarity.py
seqme/metrics/kl_divergence.py
seqme/metrics/length.py
seqme/metrics/mmd.py
seqme/metrics/novelty.py
seqme/metrics/precision_recall.py
seqme/metrics/subset.py
seqme/metrics/threshold.py
seqme/metrics/uniqueness.py
seqme/models/__init__.py
seqme/models/amino_acid_descriptors.py
seqme/models/ensemble.py
seqme/models/esm2.py
seqme/models/esm_fold.py
seqme/models/exceptions.py
seqme/models/gena_lm.py
seqme/models/hyformer.py
seqme/models/kmers.py
seqme/models/molecule_descriptors.py
seqme/models/pca.py
seqme/models/rna_fm.py
seqme/models/third_party.py
seqme/utils/__init__.py
seqme/utils/diagnostics.py
seqme/utils/projection.py
seqme/utils/sequences.py
seqme-0.4.0.dist-info/METADATA
seqme-0.4.0.dist-info/WHEEL
seqme-0.4.0.dist-info/licenses/LICENSE
seqme-0.4.0.dist-info/RECORD
