Metadata-Version: 2.4
Name: seqme
Version: 0.4.0
Summary: Metrics for evaluating biological sequence design.
Project-URL: Documentation, https://seqme.readthedocs.io
Project-URL: Source, https://github.com/szczurek-lab/seqme
Project-URL: Home-page, https://github.com/szczurek-lab/seqme
Author: Rasmus Møller-Larsen, Adam Izdebski, Jan Olszewski, Pankhil Gawade, Michal Kmicikiewicz, Wojciech Zarzecki, Ewa Szczurek
Maintainer: Rasmus Møller-Larsen
License: BSD 3-Clause License
License-File: LICENSE
Classifier: Development Status :: 4 - Beta
Classifier: Environment :: Console
Classifier: Framework :: Jupyter
Classifier: Intended Audience :: Developers
Classifier: Intended Audience :: Science/Research
Classifier: License :: OSI Approved :: BSD License
Classifier: Natural Language :: English
Classifier: Operating System :: OS Independent
Classifier: Programming Language :: Python :: 3
Classifier: Programming Language :: Python :: 3.10
Classifier: Programming Language :: Python :: 3.11
Classifier: Programming Language :: Python :: 3.12
Classifier: Programming Language :: Python :: 3.13
Classifier: Programming Language :: Python :: 3.14
Classifier: Topic :: Scientific/Engineering :: Artificial Intelligence
Classifier: Topic :: Scientific/Engineering :: Bio-Informatics
Classifier: Topic :: Scientific/Engineering :: Visualization
Requires-Python: >=3.10
Requires-Dist: matplotlib>=3.6
Requires-Dist: moocore
Requires-Dist: numpy
Requires-Dist: pandas>=1.5
Requires-Dist: polyleven
Requires-Dist: scikit-learn
Requires-Dist: scipy
Requires-Dist: torch
Requires-Dist: tqdm
Requires-Dist: umap-learn
Provides-Extra: aa-descriptors
Requires-Dist: modlamp; extra == 'aa-descriptors'
Provides-Extra: dev
Requires-Dist: ipykernel; extra == 'dev'
Requires-Dist: ipywidgets; extra == 'dev'
Requires-Dist: mypy; extra == 'dev'
Requires-Dist: nbstripout; extra == 'dev'
Requires-Dist: pre-commit>=3.0.0; extra == 'dev'
Requires-Dist: pytest; extra == 'dev'
Requires-Dist: pytest-cov; extra == 'dev'
Requires-Dist: ruff; extra == 'dev'
Provides-Extra: doc
Requires-Dist: ipykernel; extra == 'doc'
Requires-Dist: ipywidgets; extra == 'doc'
Requires-Dist: myst-nb; extra == 'doc'
Requires-Dist: myst-parser; extra == 'doc'
Requires-Dist: nbsphinx; extra == 'doc'
Requires-Dist: scanpydoc; extra == 'doc'
Requires-Dist: seaborn; extra == 'doc'
Requires-Dist: sphinx; extra == 'doc'
Requires-Dist: sphinx-autodoc-typehints; extra == 'doc'
Requires-Dist: sphinx-book-theme; extra == 'doc'
Requires-Dist: sphinx-copybutton; extra == 'doc'
Requires-Dist: sphinx-gallery; extra == 'doc'
Provides-Extra: esm2
Requires-Dist: transformers; extra == 'esm2'
Provides-Extra: esmfold
Requires-Dist: transformers; extra == 'esmfold'
Provides-Extra: genalm
Requires-Dist: einops; extra == 'genalm'
Requires-Dist: transformers; extra == 'genalm'
Provides-Extra: hyformer
Requires-Dist: einops>=0.7; extra == 'hyformer'
Requires-Dist: torchvision; extra == 'hyformer'
Requires-Dist: transformers; extra == 'hyformer'
Provides-Extra: hyformer-molecules
Requires-Dist: deepchem; extra == 'hyformer-molecules'
Requires-Dist: torchvision; extra == 'hyformer-molecules'
Requires-Dist: transformers; extra == 'hyformer-molecules'
Provides-Extra: molecule-descriptors
Requires-Dist: rdkit; extra == 'molecule-descriptors'
Provides-Extra: rnafm
Requires-Dist: rna-fm; extra == 'rnafm'
